.gitignore
LICENSE
MANIFEST.in
README.md
setup.py
docs/Makefile
docs/conf.py
docs/index.rst
docs/intro.rst
docs/lib.rst
docs/readme.md
docs/requirements.txt
docs/tools.rst
docs/lib/filtlib.rst
docs/lib/geolib.rst
docs/lib/iolib.rst
docs/lib/malib.rst
docs/lib/timelib.rst
docs/lib/warplib.rst
docs/tools/apply_mask.rst
docs/tools/clip_raster_by_shp.rst
docs/tools/make_stack.rst
docs/tools/raster2shp.rst
docs/tools/replace_ndv.rst
docs/tools/trim_ndv.rst
docs/tools/warptool.rst
pygeotools/__init__.py
pygeotools/apply_mask.py
pygeotools/clip_raster_by_shp.py
pygeotools/copyproj.py
pygeotools/filter.py
pygeotools/make_stack.py
pygeotools/mask_raster.sh
pygeotools/ogr_merge.sh
pygeotools/proj_select.py
pygeotools/raster2shp.py
pygeotools/replace_ndv.py
pygeotools/rio_test.py
pygeotools/stack2xarray.py
pygeotools/trim_ndv.py
pygeotools/warptool.py
pygeotools.egg-info/PKG-INFO
pygeotools.egg-info/SOURCES.txt
pygeotools.egg-info/dependency_links.txt
pygeotools.egg-info/requires.txt
pygeotools.egg-info/top_level.txt
pygeotools/lib/__init__.py
pygeotools/lib/filtlib.py
pygeotools/lib/geolib.py
pygeotools/lib/iolib.py
pygeotools/lib/malib.py
pygeotools/lib/timelib.py
pygeotools/lib/warplib.py
tutorial/python_seminar.sh