Metadata-Version: 2.1
Name: pygeotools
Version: 1.1.1
Summary: Libraries and command-line utilities for geospatial data processing/analysis
Home-page: https://github.com/dshean/pygeotools
Author: David Shean
Author-email: dshean@gmail.com
License: MIT
License-File: LICENSE
Requires-Dist: gdal
Requires-Dist: numpy
Requires-Dist: scipy
Requires-Dist: matplotlib
